{
  "id": "177",
  "isTestnet": false,
  "sortIndex": 440,
  "name": "HashKey Chain",
  "themeColor": "#505050",
  "logo": "https://raw.githubusercontent.com/TalismanSociety/chaindata/main/assets/chains/unknown.svg",
  "nativeToken": null,
  "tokens": [],
  "explorerUrl": "https://explorer.hsk.xyz",
  "rpcs": [
    {
      "url": "https://mainnet.hsk.xyz"
    }
  ],
  "substrateChain": null,
  "balancesConfig": [
    {
      "moduleType": "evm-native",
      "moduleConfig": {
        "symbol": "HSK",
        "decimals": 18,
        "logo": "https://raw.githubusercontent.com/TalismanSociety/chaindata/main/assets/tokens/unknown.svg"
      }
    }
  ],
  "balancesMetadata": [],
  "isDefault": false
}