{
  "id": "31754",
  "isTestnet": true,
  "sortIndex": 1849,
  "name": "Xchain Testnet",
  "themeColor": "#505050",
  "logo": "https://raw.githubusercontent.com/TalismanSociety/chaindata/main/assets/chains/unknown.svg",
  "nativeToken": null,
  "tokens": [],
  "explorerUrl": "https://xchaintest.net",
  "rpcs": [
    {
      "url": "https://rpc.xchaintest.net"
    }
  ],
  "substrateChain": null,
  "balancesConfig": [
    {
      "moduleType": "evm-native",
      "moduleConfig": {
        "symbol": "INTD",
        "decimals": 18,
        "logo": "https://raw.githubusercontent.com/TalismanSociety/chaindata/main/assets/tokens/unknown.svg"
      }
    }
  ],
  "balancesMetadata": [],
  "isDefault": false
}