{
  "id": "7077",
  "isTestnet": true,
  "sortIndex": 1715,
  "name": "Planq Atlas Testnet",
  "themeColor": "#3d587a",
  "logo": "https://raw.githubusercontent.com/TalismanSociety/chaindata/main/assets/chains/known/planq.webp",
  "nativeToken": null,
  "tokens": [],
  "explorerUrl": null,
  "rpcs": [
    {
      "url": "https://evm-rpc-atlas.planq.network"
    }
  ],
  "substrateChain": null,
  "balancesConfig": [
    {
      "moduleType": "evm-native",
      "moduleConfig": {
        "symbol": "tPLQ",
        "decimals": 18,
        "logo": "https://raw.githubusercontent.com/TalismanSociety/chaindata/main/assets/tokens/unknown.svg"
      }
    }
  ],
  "balancesMetadata": [],
  "isDefault": false
}