{
  "id": "71111",
  "isTestnet": false,
  "sortIndex": 424,
  "name": "GuapcoinX",
  "themeColor": "#f8f8ef",
  "logo": "https://raw.githubusercontent.com/TalismanSociety/chaindata/main/assets/chains/known/guapcoinx.webp",
  "nativeToken": null,
  "tokens": [],
  "explorerUrl": "http://explorer.guapcoinx.com",
  "rpcs": [
    {
      "url": "https://rpc-mainnet.guapcoinx.com/"
    },
    {
      "url": "https://rpc-mainnet-1.guapcoinx.com/"
    },
    {
      "url": "https://rpc-mainnet-2.guapcoinx.com/"
    }
  ],
  "substrateChain": null,
  "balancesConfig": [
    {
      "moduleType": "evm-native",
      "moduleConfig": {
        "symbol": "GuapX",
        "decimals": 18,
        "logo": "https://raw.githubusercontent.com/TalismanSociety/chaindata/main/assets/tokens/unknown.svg"
      }
    }
  ],
  "balancesMetadata": [],
  "isDefault": false
}