{
  "id": "743111",
  "isTestnet": true,
  "sortIndex": 1460,
  "name": "Hemi Sepolia",
  "themeColor": "#ff6c15",
  "logo": "https://raw.githubusercontent.com/TalismanSociety/chaindata/main/assets/chains/known/hemi.webp",
  "nativeToken": null,
  "tokens": [],
  "explorerUrl": "https://testnet.explorer.hemi.xyz",
  "rpcs": [
    {
      "url": "https://testnet.rpc.hemi.network/rpc"
    }
  ],
  "substrateChain": null,
  "balancesConfig": [
    {
      "moduleType": "evm-native",
      "moduleConfig": {
        "symbol": "ETH",
        "decimals": 18,
        "logo": "https://raw.githubusercontent.com/TalismanSociety/chaindata/main/assets/tokens/eth.svg"
      }
    }
  ],
  "balancesMetadata": [],
  "isDefault": false
}