{
  "id": "7762959",
  "isTestnet": false,
  "sortIndex": 400,
  "name": "Musicoin",
  "themeColor": "#505050",
  "logo": "https://raw.githubusercontent.com/TalismanSociety/chaindata/main/assets/chains/unknown.svg",
  "nativeToken": null,
  "tokens": [],
  "explorerUrl": null,
  "rpcs": [
    {
      "url": "https://mewapi.musicoin.tw"
    }
  ],
  "substrateChain": null,
  "balancesConfig": [
    {
      "moduleType": "evm-native",
      "moduleConfig": {
        "symbol": "MUSIC",
        "decimals": 18,
        "logo": "https://raw.githubusercontent.com/TalismanSociety/chaindata/main/assets/tokens/unknown.svg"
      }
    }
  ],
  "balancesMetadata": [],
  "isDefault": false
}