{
  "id": "78431",
  "isTestnet": true,
  "sortIndex": 764,
  "name": "Bulletin Subnet",
  "themeColor": "#505050",
  "logo": "https://raw.githubusercontent.com/TalismanSociety/chaindata/main/assets/chains/unknown.svg",
  "nativeToken": null,
  "tokens": [],
  "explorerUrl": "https://subnets-test.avax.network/bulletin",
  "rpcs": [
    {
      "url": "https://subnets.avax.network/bulletin/testnet/rpc"
    }
  ],
  "substrateChain": null,
  "balancesConfig": [
    {
      "moduleType": "evm-native",
      "moduleConfig": {
        "symbol": "BLT",
        "decimals": 18,
        "logo": "https://raw.githubusercontent.com/TalismanSociety/chaindata/main/assets/tokens/unknown.svg"
      }
    }
  ],
  "balancesMetadata": [],
  "isDefault": false
}