{
  "id": "26",
  "isTestnet": true,
  "sortIndex": 1044,
  "name": "Genesis L1 testnet",
  "themeColor": "#505050",
  "logo": "https://raw.githubusercontent.com/TalismanSociety/chaindata/main/assets/chains/unknown.svg",
  "nativeToken": null,
  "tokens": [],
  "explorerUrl": "https://testnet.genesisl1.org",
  "rpcs": [
    {
      "url": "https://testrpc.genesisl1.org"
    }
  ],
  "substrateChain": null,
  "balancesConfig": [
    {
      "moduleType": "evm-native",
      "moduleConfig": {
        "symbol": "L1test",
        "decimals": 18,
        "logo": "https://raw.githubusercontent.com/TalismanSociety/chaindata/main/assets/tokens/unknown.svg"
      }
    }
  ],
  "balancesMetadata": [],
  "isDefault": false
}